{
  "C": {
    "variables":[
      "#include <stdio.h>\nint main(){ int a=10; float b=3.5; char c='A'; printf(\"%d %f %c\\n\",a,b,c); return 0; }",
      "#include <stdio.h>\nint main(){ int x=5,y=15; printf(\"%d\\n\",x+y); return 0; }",
      "#include <stdio.h>\nint main(){ double pi=3.1416,radius=5; double area=pi*radius*radius; printf(\"%lf\\n\",area); return 0; }",
      "#include <stdio.h>\nint main(){ char grade='B'; printf(\"%c\\n\",grade); return 0; }",
      "#include <stdio.h>\nint main(){ long population=7800000000; printf(\"%ld\\n\",population); return 0; }"
    ],
    "condition":[
      "#include <stdio.h>\nint main(){ int x=10; if(x>5) printf(\"Greater\\n\"); else printf(\"Smaller\\n\"); return 0; }",
      "#include <stdio.h>\nint main(){ int n=2; switch(n){case 1: printf(\"1\\n\"); break; case 2: printf(\"2\\n\"); break; default: printf(\"0\\n\");} return 0; }",
      "#include <stdio.h>\nint main(){ int age=18; printf(age>=18 ? \"Adult\\n\" : \"Minor\\n\"); return 0; }",
      "#include <stdio.h>\nint main(){ int score=85; if(score>=90) printf(\"A\\n\"); else if(score>=75) printf(\"B\\n\"); else printf(\"C\\n\"); return 0; }",
      "#include <stdio.h>\nint main(){ int num=-5; printf(num<0 ? \"Negative\\n\" : \"Positive\\n\"); return 0; }"
    ],
    "loop_for":[
      "#include <stdio.h>\nint main(){ for(int i=0;i<5;i++) printf(\"%d\\n\",i); return 0; }",
      "#include <stdio.h>\nint main(){ int sum=0; for(int i=1;i<=10;i++) sum+=i; printf(\"%d\\n\",sum); return 0; }",
      "#include <stdio.h>\nint main(){ for(int i=10;i>0;i--) printf(\"%d\\n\",i); return 0; }",
      "#include <stdio.h>\nint main(){ for(int i=1;i<=5;i++){ for(int j=1;j<=i;j++) printf(\"*\"); printf(\"\\n\"); } return 0; }",
      "#include <stdio.h>\nint main(){ int arr[5]={1,2,3,4,5}; for(int i=0;i<5;i++) printf(\"%d\\n\",arr[i]); return 0; }"
    ],
    "loop_while":[
      "#include <stdio.h>\nint main(){ int i=0; while(i<5){ printf(\"%d\\n\",i); i++; } return 0; }",
      "#include <stdio.h>\nint main(){ int n=1,sum=0; while(n<=10){ sum+=n; n++; } printf(\"%d\\n\",sum); return 0; }",
      "#include <stdio.h>\nint main(){ int i=10; while(i>0){ printf(\"%d\\n\",i); i--; } return 0; }",
      "#include <stdio.h>\nint main(){ int i=1; while(i<=5){ printf(\"%d\\n\",i*i); i++; } return 0; }",
      "#include <stdio.h>\nint main(){ int n=1; while(n<=10){ if(n%2==0) printf(\"%d\\n\",n); n++; } return 0; }"
    ],
    "loop_do_while":[
      "#include <stdio.h>\nint main(){ int i=0; do{ printf(\"%d\\n\",i); i++; }while(i<5); return 0; }",
      "#include <stdio.h>\nint main(){ int i=1,sum=0; do{ sum+=i; i++; }while(i<=10); printf(\"%d\\n\",sum); return 0; }",
      "#include <stdio.h>\nint main(){ int i=10; do{ printf(\"%d\\n\",i); i--; }while(i>0); return 0; }",
      "#include <stdio.h>\nint main(){ int i=1; do{ printf(\"%d\\n\",i*i); i++; }while(i<=5); return 0; }",
      "#include <stdio.h>\nint main(){ int n=1; do{ if(n%2!=0) printf(\"%d\\n\",n); n++; }while(n<=10); return 0; }"
    ],
    "array":[
      "#include <stdio.h>\nint main(){ int arr[5]={1,2,3,4,5}; for(int i=0;i<5;i++) printf(\"%d\\n\",arr[i]); return 0; }",
      "#include <stdio.h>\nint main(){ char letters[3]={'A','B','C'}; for(int i=0;i<3;i++) printf(\"%c\\n\",letters[i]); return 0; }",
      "#include <stdio.h>\nint main(){ float nums[4]={1.1,2.2,3.3,4.4}; for(int i=0;i<4;i++) printf(\"%f\\n\",nums[i]); return 0; }",
      "#include <stdio.h>\nint main(){ int arr[5]; for(int i=0;i<5;i++) arr[i]=i*i; for(int i=0;i<5;i++) printf(\"%d\\n\",arr[i]); return 0; }",
      "#include <stdio.h>\nint main(){ int arr[5]={0}; for(int i=0;i<5;i++) arr[i]=i+1; for(int i=0;i<5;i++) printf(\"%d\\n\",arr[i]); return 0; }"
    ],
    "string":[
      "#include <stdio.h>\n#include <string.h>\nint main(){ char str[20]=\"Hello\"; printf(\"%s\\n\",str); return 0; }",
      "#include <stdio.h>\n#include <string.h>\nint main(){ char s1[20]=\"Hi\"; char s2[20]=\"There\"; strcat(s1,s2); printf(\"%s\\n\",s1); return 0; }",
      "#include <stdio.h>\n#include <string.h>\nint main(){ char str[]=\"Hello World\"; printf(\"Length: %lu\\n\",strlen(str)); return 0; }",
      "#include <stdio.h>\n#include <string.h>\nint main(){ char str[]=\"Hello\"; strcpy(str,\"Hi\"); printf(\"%s\\n\",str); return 0; }",
      "#include <stdio.h>\n#include <string.h>\nint main(){ char str1[]=\"abc\"; char str2[]=\"xyz\"; int cmp=strcmp(str1,str2); printf(\"%d\\n\",cmp); return 0; }"
    ],
    "function":[
      "#include <stdio.h>\nint add(int a,int b){ return a+b; }\nint main(){ printf(\"%d\\n\",add(3,5)); return 0; }",
      "#include <stdio.h>\nvoid greet(){ printf(\"Hello World\\n\"); }\nint main(){ greet(); return 0; }",
      "#include <stdio.h>\nint square(int x){ return x*x; }\nint main(){ printf(\"%d\\n\",square(4)); return 0; }",
      "#include <stdio.h>\nint factorial(int n){ if(n<=1) return 1; else return n*factorial(n-1); }\nint main(){ printf(\"%d\\n\",factorial(5)); return 0; }",
      "#include <stdio.h>\nvoid swap(int *a,int *b){ int t=*a; *a=*b; *b=t; }\nint main(){ int x=3,y=5; swap(&x,&y); printf(\"%d %d\\n\",x,y); return 0; }"
    ],
    "structure":[
      "#include <stdio.h>\nstruct Point{ int x; int y; };\nint main(){ struct Point p={2,3}; printf(\"%d %d\\n\",p.x,p.y); return 0; }",
      "#include <stdio.h>\nstruct Person{ char name[20]; int age; };\nint main(){ struct Person p={\"Alice\",25}; printf(\"%s %d\\n\",p.name,p.age); return 0; }",
      "#include <stdio.h>\nstruct Rectangle{ int l; int w; };\nint main(){ struct Rectangle r={5,10}; printf(\"Area: %d\\n\",r.l*r.w); return 0; }",
      "#include <stdio.h>\nstruct Point{ int x; int y; };\nint main(){ struct Point arr[2]={{1,2},{3,4}}; printf(\"%d %d\\n\",arr[1].x,arr[1].y); return 0; }",
      "#include <stdio.h>\nstruct Circle{ int r; };\nint main(){ struct Circle c={5}; printf(\"Radius: %d\\n\",c.r); return 0; }"
    ],
    "file":[
      "#include <stdio.h>\nint main(){ FILE *f=fopen(\"file.txt\",\"w\"); fprintf(f,\"Hello\\n\"); fclose(f); return 0; }",
      "#include <stdio.h>\nint main(){ FILE *f=fopen(\"file.txt\",\"r\"); char s[100]; fgets(s,100,f); printf(\"%s\",s); fclose(f); return 0; }",
      "#include <stdio.h>\nint main(){ FILE *f=fopen(\"file.txt\",\"w\"); for(int i=0;i<5;i++) fprintf(f,\"%d\\n\",i); fclose(f); return 0; }",
      "#include <stdio.h>\nint main(){ FILE *f=fopen(\"file.txt\",\"r\"); int x; fscanf(f,\"%d\",&x); printf(\"%d\\n\",x); fclose(f); return 0; }",
      "#include <stdio.h>\nint main(){ FILE *f=fopen(\"file.txt\",\"w+\"); fprintf(f,\"Line1\\n\"); fseek(f,0,SEEK_SET); char s[20]; fgets(s,20,f); printf(\"%s\",s); fclose(f); return 0; }"
    ],
    "math_function":[
      "#include <stdio.h>\n#include <math.h>\nint main(){ double x=9; printf(\"%lf\\n\",sqrt(x)); return 0; }",
      "#include <stdio.h>\n#include <math.h>\nint main(){ double x=2; printf(\"%lf\\n\",pow(x,3)); return 0; }",
      "#include <stdio.h>\n#include <math.h>\nint main(){ double angle=45; printf(\"%lf\\n\",sin(angle*3.1416/180)); return 0; }",
      "#include <stdio.h>\n#include <math.h>\nint main(){ double val=-5; printf(\"%lf\\n\",fabs(val)); return 0; }",
      "#include <stdio.h>\n#include <math.h>\nint main(){ double x=7.3; printf(\"%lf\\n\",ceil(x)); return 0; }"
    ]
  }
}
